pyplanemono/__init__.py
pyplanemono/elements/__init__.py
pyplanemono/elements/grating.py
pyplanemono/elements/mirror.py
pyplanemono/elements/pgm.py
pyplanemono/geometry/__init__.py
pyplanemono/geometry/geometry.py
pyplanemono/gui/__init__.py
pyplanemono/gui/drag.py
pyplanemono/gui/gui_widgets.py
pyplanemono/gui/main.py
pyplanemono/gui/mplwidgets.py
pyplanemono/shadow/__init__.py
pyplanemono/shadow/analysis.py
pyplanemono/shadow/b07test.py
pyplanemono/shadow/tools.py
pyplanemono-1.0.dist-info/LICENSE
pyplanemono-1.0.dist-info/METADATA
pyplanemono-1.0.dist-info/WHEEL
pyplanemono-1.0.dist-info/top_level.txt
pyplanemono-1.0.dist-info/RECORD
