Metadata-Version: 2.1
Name: pyplanemono
Version: 1.0
Summary: X-ray tracing for plane grating monochromator
Author-email: Patrick Wang <patrick.wang@diamond.ac.uk>
Classifier: Programming Language :: Python :: 3
Classifier: License :: OSI Approved :: MIT License
Classifier: Operating System :: OS Independent
Requires-Python: >=3.8.0
License-File: LICENSE
Requires-Dist: numpy >=1.21
Requires-Dist: scipy >=1.8.1
Requires-Dist: matplotlib <=3.5.3,>=3.3.2
Requires-Dist: dill >=0.3.6
Requires-Dist: colorama >=0.4.4
Requires-Dist: pyrsistent >=0.19.3
